Workbook

Sheet Raw Data
A1: Row ID | B1: Order ID | C1: Order Date | D1: Ship Date | E1: Ship Mode | F1: Customer ID | G1: Customer Name | H1: Segment | I1: Country | J1: City | K1: State | L1: Postal Code | M1: Region | N1: Product ID | O1: Category | P1: Sub-Category | Q1: Product Name | R1: Sales | S1: Quantity | T1: Discount | U1: Profit | V1: Order Year | W1: Order Month | X1: Order Quarter | Y1: Ship Days | Z1: Profit Margin | AA1: Revenue
A2: 1 | B2: CA-2016-152156 | C2: 2016-11-08 | D2: 2016-11-11 | E2: Second Class | F2: CG-12520 | G2: Claire Gute | H2: Consumer | I2: United States | J2: Henderson | K2: Kentucky | L2: 42420 | M2: South | N2: FUR-BO-10001798 | O2: Furniture | P2: Bookcases | Q2: Bush Somerset Collection Bookcase | R2: 261.96 | S2: 2 | T2: 0 | U2: 41.9136 | V2: 2016 | W2: 11 | X2: 4 | Y2: 3 | Z2: 16 | AA2: 261.96
A3: 2 | B3: CA-2016-152156 | C3: 2016-11-08 | D3: 2016-11-11 | E3: Second Class | F3: CG-12520 | G3: Claire Gute | H3: Consumer | I3: United States | J3: Henderson | K3: Kentucky | L3: 42420 | M3: South | N3: FUR-CH-10000454 | O3: Furniture | P3: Chairs | Q3: Hon Deluxe Fabric Upholstered Stacking Chairs | R3: 731.94 | S3: 3 | T3: 0 | U3: 219.582 | V3: 2016 | W3: 11 | X3: 4 | Y3: 3 | Z3: 30 | AA3: 731.94
A4: 3 | B4: CA-2016-138688 | C4: 2016-06-12 | D4: 2016-06-16 | E4: Second Class | F4: DV-13045 | G4: Darrin Van Huff | H4: Corporate | I4: United States | J4: Los Angeles | K4: California | L4: 90036 | M4: West | N4: OFF-LA-10000240 | O4: Office Supplies | P4: Labels | Q4: Self-Adhesive Address Labels for Typewriters by Universal | R4: 14.62 | S4: 2 | T4: 0 | U4: 6.8714 | V4: 2016 | W4: 6 | X4: 2 | Y4: 4 | Z4: 47 | AA4: 14.62
A5: 4 | B5: US-2015-108966 | C5: 2015-10-11 | D5: 2015-10-18 | E5: Standard Class | F5: SO-20335 | G5: Sean O'Donnell | H5: Consumer | I5: United States | J5: Fort Lauderdale | K5: Florida | L5: 33311 | M5: South | N5: FUR-TA-10000577 | O5: Furniture | P5: Tables | Q5: Bretford CR4500 Series Slim Rectangular Table | R5: 957.5775 | S5: 5 | T5: 0.45 | U5: -383.031 | V5: 2015 | W5: 10 | X5: 4 | Y5: 7 | Z5: -40 | AA5: 957.5775
A6: 5 | B6: US-2015-108966 | C6: 2015-10-11 | D6: 2015-10-18 | E6: Standard Class | F6: SO-20335 | G6: Sean O'Donnell | H6: Consumer | I6: United States | J6: Fort Lauderdale | K6: Florida | L6: 33311 | M6: South | N6: OFF-ST-10000760 | O6: Office Supplies | P6: Storage | Q6: Eldon Fold 'N Roll Cart System | R6: 22.368 | S6: 2 | T6: 0.2 | U6: 2.5164 | V6: 2015 | W6: 10 | X6: 4 | Y6: 7 | Z6: 11.25 | AA6: 22.368
A7: 6 | B7: CA-2014-115812 | C7: 2014-06-09 | D7: 2014-06-14 | E7: Standard Class | F7: BH-11710 | G7: Brosina Hoffman | H7: Consumer | I7: United States | J7: Los Angeles | K7: California | L7: 90032 | M7: West | N7: FUR-FU-10001487 | O7: Furniture | P7: Furnishings | Q7: Eldon Expressions Wood and Plastic Desk Accessories Mahogany | R7: 48.86 | S7: 7 | T7: 0 | U7: 14.1694 | V7: 2014 | W7: 6 | X7: 2 | Y7: 5 | Z7: 29 | AA7: 48.86
A8: 7 | B8: CA-2014-115812 | C8: 2014-06-09 | D8: 2014-06-14 | E8: Standard Class | F8: BH-11710 | G8: Brosina Hoffman | H8: Consumer | I8: United States | J8: Los Angeles | K8: California | L8: 90032 | M8: West | N8: OFF-AR-10002833 | O8: Office Supplies | P8: Art | Q8: Newell 322 | R8: 7.28 | S8: 4 | T8: 0 | U8: 1.9656 | V8: 2014 | W8: 6 | X8: 2 | Y8: 5 | Z8: 27 | AA8: 7.28
A9: 8 | B9: CA-2014-115812 | C9: 2014-06-09 | D9: 2014-06-14 | E9: Standard Class | F9: BH-11710 | G9: Brosina Hoffman | H9: Consumer | I9: United States | J9: Los Angeles | K9: California | L9: 90032 | M9: West | N9: TEC-PH-10002275 | O9: Technology | P9: Phones | Q9: Mitel 5320 IP Phone VoIP phone | R9: 907.152 | S9: 6 | T9: 0.2 | U9: 90.7152 | V9: 2014 | W9: 6 | X9: 2 | Y9: 5 | Z9: 10 | AA9: 907.152
A10: 9 | B10: CA-2014-112326 | C10: 2014-09-07 | D10: 2014-09-11 | E10: Standard Class | F10: AA-10480 | G10: Andrew Allen | H10: Consumer | I10: United States | J10: Concord | K10: North Carolina | L10: 28027 | M10: South | N10: OFF-BI-10003910 | O10: Office Supplies | P10: Binders | Q10: DXL Angle-View Binders with Locking Rings by Samsill | R10: 18.504 | S10: 3 | T10: 0.2 | U10: 5.7825 | V10: 2014 | W10: 9 | X10: 3 | Y10: 4 | Z10: 31.25 | AA10: 18.504
A11: 10 | B11: US-2016-112326 | C11: 2016-06-17 | D11: 2016-06-22 | E11: Standard Class | F11: IM-15070 | G11: Irene Maddox | H11: Consumer | I11: United States | J11: Seattle | K11: Washington | L11: 98103 | M11: West | N11: OFF-AP-10002311 | O11: Office Supplies | P11: Appliances | Q11: Hoover Replacement Belt for Commercial Guardsman Heavy-Duty Upright Vacuum | R11: 114.9 | S11: 5 | T11: 0 | U11: 34.47 | V11: 2016 | W11: 6 | X11: 2 | Y11: 5 | Z11: 30 | AA11: 114.9
A12: 11 | B12: CA-2015-135545 | C12: 2015-01-21 | D12: 2015-01-23 | E12: Second Class | F12: DP-13000 | G12: Darren Powers | H12: Consumer | I12: Canada | J12: Oshawa | K12: Ontario | L12: L1H | M12: Central | N12: TEC-AC-10003027 | O12: Technology | P12: Accessories | Q12: Verbatim 25 GB 6x Blu-ray Single-Layer Recordable Disc 25-Pack Spindle | R12: 71.372 | S12: 3 | T12: 0.2 | U12: 1.0496 | V12: 2015 | W12: 1 | X12: 1 | Y12: 2 | Z12: 1.47 | AA12: 71.372
A13: 12 | B13: CA-2016-105893 | C13: 2016-11-11 | D13: 2016-11-15 | E13: Standard Class | F13: KH-16510 | G13: Ken Heidel | H13: Home Office | I13: United States | J13: Portland | K13: Oregon | L13: 97206 | M13: West | N13: OFF-PA-10004041 | O13: Office Supplies | P13: Paper | Q13: Xerox 1967 | R13: 15.552 | S13: 3 | T13: 0.2 | U13: 5.4432 | V13: 2016 | W13: 11 | X13: 4 | Y13: 4 | Z13: 35 | AA13: 15.552
... A51: 50 | B51: CA-2014-152223 | C51: 2014-05-30 | D51: 2014-06-03 | E51: Standard Class | F51: MS-17920 | G51: Mark Stevenson | H51: Consumer | I51: United States | J51: Oakland | K51: California | L51: 94609 | M51: West | N51: OFF-ST-10004123 | O51: Office Supplies | P51: Storage | Q51: Smead Lockit Folder Two Fasteners 1/3 Cut Top Tab Letter | R51: 73.12 | S51: 4 | T51: 0.2 | U51: 14.624 | V51: 2014 | W51: 5 | X51: 2 | Y51: 4 | Z51: 20 | AA51: 73.12

Sheet Executive Summary
A1: GLOBAL SUPERSTORE - EXECUTIVE DASHBOARD
A2: Report Date: February 16, 2026
A5: KEY PERFORMANCE INDICATORS
A6: Total Sales | B6: =SUM('Raw Data'!R:R)
A7: Total Profit | B7: =SUM('Raw Data'!U:U)
A8: Overall Profit Margin | B8: =IFERROR(B7/B6,0)
A9: Total Orders | B9: =COUNTA('Raw Data'!B:B)-1
A10: Average Order Value | B10: =IFERROR(B6/B9,0)
A13: SALES BY CATEGORY | B13: Sales | C13: Profit | D13: Margin %
A14: Furniture | B14: =SUMIF('Raw Data'!O:O,A14,'Raw Data'!R:R) | C14: =SUMIF('Raw Data'!O:O,A14,'Raw Data'!U:U) | D14: =C14/B14
A15: Office Supplies | B15: =SUMIF('Raw Data'!O:O,A15,'Raw Data'!R:R) | C15: =SUMIF('Raw Data'!O:O,A15,'Raw Data'!U:U) | D15: =C15/B15
A16: Technology | B16: =SUMIF('Raw Data'!O:O,A16,'Raw Data'!R:R) | C16: =SUMIF('Raw Data'!O:O,A16,'Raw Data'!U:U) | D16: =C16/B16
A19: SALES BY REGION | B19: Sales | C19: Profit
A20: Africa | B20: =SUMIF('Raw Data'!M:M,A20,'Raw Data'!R:R) | C20: =SUMIF('Raw Data'!M:M,A20,'Raw Data'!U:U)
A21: Asia | B21: =SUMIF('Raw Data'!M:M,A21,'Raw Data'!R:R) | C21: =SUMIF('Raw Data'!M:M,A21,'Raw Data'!U:U)
A22: Central | B22: =SUMIF('Raw Data'!M:M,A22,'Raw Data'!R:R) | C22: =SUMIF('Raw Data'!M:M,A22,'Raw Data'!U:U)
A23: East | B23: =SUMIF('Raw Data'!M:M,A23,'Raw Data'!R:R) | C23: =SUMIF('Raw Data'!M:M,A23,'Raw Data'!U:U)
A24: Europe | B24: =SUMIF('Raw Data'!M:M,A24,'Raw Data'!R:R) | C24: =SUMIF('Raw Data'!M:M,A24,'Raw Data'!U:U)
A25: LATAM | B25: =SUMIF('Raw Data'!M:M,A25,'Raw Data'!R:R) | C25: =SUMIF('Raw Data'!M:M,A25,'Raw Data'!U:U)
A26: Oceania | B26: =SUMIF('Raw Data'!M:M,A26,'Raw Data'!R:R) | C26: =SUMIF('Raw Data'!M:M,A26,'Raw Data'!U:U)
A27: South | B27: =SUMIF('Raw Data'!M:M,A27,'Raw Data'!R:R) | C27: =SUMIF('Raw Data'!M:M,A27,'Raw Data'!U:U)
A28: West | B28: =SUMIF('Raw Data'!M:M,A28,'Raw Data'!R:R) | C28: =SUMIF('Raw Data'!M:M,A28,'Raw Data'!U:U)

Sheet Sales Analysis
A1: CATEGORY PERFORMANCE ANALYSIS
A3: Category | B3: Total Sales | C3: Total Profit | D3: Profit Margin % | E3: Number of Orders
A5: Technology | B5: 9249.32 | C5: 2123.76 | D5: 0.2296 | E5: 14
A6: Furniture | B6: 6207.51 | C6: -2272.13 | D6: -0.366 | E6: 9
A7: Office Supplies | B7: 1426.06 | C7: 409.2 | D7: 0.2869 | E7: 23
A12: REGIONAL PERFORMANCE ANALYSIS
A14: Region | B14: Total Sales | C14: Total Profit | D14: Profit Margin %
A16: South | B16: 5606.82 | C16: 182.28 | D16: 0.0325
A17: Asia | B17: 4167.73 | C17: -1418.31 | D17: -0.3403
A18: LATAM | B18: 2323.47 | C18: 649.47 | D18: 0.2795
A19: West | B19: 1295.45 | C19: 179.66 | D19: 0.1387
A20: Central | B20: 1144.39 | C20: 267.89 | D20: 0.2341
A21: Africa | B21: 1132.6 | C21: 208.89 | D21: 0.1844
A22: East | B22: 949.9 | C22: 79.68 | D22: 0.0839
A23: Europe | B23: 255.39 | C23: 108.13 | D23: 0.4234
A24: Oceania | B24: 7.14 | C24: 3.14 | D24: 0.4398

Sheet Profitability Analysis
A1: PROFITABILITY ANALYSIS
A3: TOP PRODUCTS BY REVENUE (sorted by sales)
A4: Product Name | B4: Total Sales | C4: Total Profit | D4: Profit Margin %
A6: Bush Advantage Collection Racetrack Conference Table | B6: 2573.82 | C6: -1716.81 | D6: -0.667028
A7: Canon imageCLASS 2200 Advanced Copier | B7: 1999.99 | C7: 600 | D7: 0.3000015
A8: Canon PC1080F Personal Copier | B8: 1999.99 | C8: 600 | D8: 0.3000015
A9: Cisco SPA525G2 5-Line IP Phone | B9: 1097.54 | C9: 219.51 | D9: 0.20000182
A10: HON 94000 Series Round Tables | B10: 1044.63 | C10: -418.93 | D10: -0.40103194
A11: Bretford CR4500 Series Slim Rectangular Table | B11: 957.58 | C11: -383.03 | D11: -0.39999791
A12: Cisco SPA 501G IP Phone | B12: 911.42 | C12: 68.36 | D12: 0.07500384
A13: Mitel 5320 IP Phone VoIP phone | B13: 907.15 | C13: 90.72 | D13: 0.10000551
A14: Hon Deluxe Fabric Upholstered Stacking Chairs | B14: 731.94 | C14: 219.58 | D14: 0.29999727
A15: Ativa V4110MDD Micro-Cut Shredder | B15: 599.99 | C15: 180 | D15: 0.300005

Sheet Advanced Formulas
A1: ADVANCED EXCEL FORMULAS EXAMPLES
A4: CALCULATION TYPE | B4: FORMULA | C4: RESULT
A5: Total Sales (SUMIF by Category) | B5: =SUMIF('Raw Data'!O:O,"Technology",'Raw Data'!R:R) | C5: =SUMIF('Raw Data'!O:O,"Technology",'Raw Data'!R:R)
A6: Average Order Value | B6: {=SUM('Raw Data'!R:R)/COUNTA(_xlfn.UNIQUE('Raw Data'!B:B))} | C6: =SUM('Raw Data'!R:R)/(COUNTA('Raw Data'!B:B)-1)
A7: Profit Margin % | B7: =SUM(Profit)/SUM(Sales) | C7: =SUM('Raw Data'!U:U)/SUM('Raw Data'!R:R)
A8: Count of Orders (Technology) | B8: =COUNTIF('Raw Data'!O:O,"Technology") | C8: =COUNTIF('Raw Data'!O:O,"Technology")
A9: Maximum Sales Value | B9: =MAX('Raw Data'!R:R) | C9: =MAX('Raw Data'!R:R)
A10: Minimum Profit Value | B10: =MIN('Raw Data'!U:U) | C10: =MIN('Raw Data'!U:U)
A12: VLOOKUP EXAMPLES
A13: Enter Order ID: | B13: CA-2016-152156
A14: Customer Name: | B14: =IFERROR(INDEX('Raw Data'!G:G,MATCH(B13,'Raw Data'!B:B,0)),"Not Found")

Sheet Instructions
A1: HOW TO USE THIS WORKBOOK
A4: SHEET DESCRIPTIONS:
A6: 1. Raw Data - Complete dataset with all sales transactions
A7: • Use filters to explore specific segments
A8: • All formulas in other sheets reference this data
A10: 2. Executive Summary - High-level KPIs and metrics
A11: • Auto-calculated from Raw Data using SUMIF and other formulas
A12: • Perfect for quick business overview
A14: 3. Sales Analysis - Detailed breakdown by category and region
A15: • Conditional formatting highlights profitable/unprofitable areas
A17: 4. Profitability Analysis - Product-level profit analysis
A18: • Identifies top performing and underperforming products
... A43: For questions or support, refer to Excel documentation.
